p2v.py
p2v_clock.py
p2v_cocotb.py
p2v_connect.py
p2v_fsm.py
p2v_misc.py
p2v_signal.py
p2v_struct.py
p2v_tb.py
p2v_tools.py
p2v_compiler-0.24.0.dist-info/licenses/LICENSE
p2v_compiler-0.24.0.dist-info/METADATA
p2v_compiler-0.24.0.dist-info/WHEEL
p2v_compiler-0.24.0.dist-info/top_level.txt
p2v_compiler-0.24.0.dist-info/RECORD
