Metadata-Version: 2.4
Name: p2v-compiler
Version: 0.24.0
Summary: A Python library for converting Python to synthesizable Verilog code
Home-page: https://github.com/eyalhoc/p2v
Author: Eyal Hochberg
Author-email: eyalhoc@gmail.com
License: GPL-3.0-or-later
Classifier: Programming Language :: Python :: 3
Classifier: License :: OSI Approved :: GNU General Public License v3 (GPLv3)
Classifier: Operating System :: OS Independent
Requires-Python: >=3.6
License-File: LICENSE
Requires-Dist: pyslang>=8.0.0
Dynamic: author
Dynamic: author-email
Dynamic: classifier
Dynamic: description
Dynamic: description-content-type
Dynamic: home-page
Dynamic: license
Dynamic: license-file
Dynamic: requires-dist
Dynamic: requires-python
Dynamic: summary
